social_regexp/__init__.py
social_regexp/constants.py
social_regexp/processing.py
social_regexp/py.typed
social_regexp-0.2.1.dist-info/LICENSE
social_regexp-0.2.1.dist-info/WHEEL
social_regexp-0.2.1.dist-info/METADATA
social_regexp-0.2.1.dist-info/RECORD
