Metadata-Version: 2.1
Name: social-regexp
Version: 0.2.1
Summary: Regexps for social data
Home-page: https://github.com/TezRomacH/social-regexp
License: MIT
Author: TezRomacH
Author-email: tez.romach@gmail.com
Requires-Python: >=3.7,<4.0
Classifier: Development Status :: 3 - Alpha
Classifier: Intended Audience :: Developers
Classifier: License :: OSI Approved :: MIT License
Classifier: Operating System :: OS Independent
Classifier: Programming Language :: Python :: 3
Classifier: Programming Language :: Python :: 3.7
Classifier: Programming Language :: Python :: 3.8
Classifier: Programming Language :: Python :: 3.9
Classifier: Topic :: Software Development :: Libraries :: Python Modules
Requires-Dist: importlib_metadata (>=1.6,<4.0); python_version < "3.8"
Project-URL: Repository, https://github.com/TezRomacH/social-regexp
